ohmylamb/__init__.py
ohmylamb/ohmylamb.py
ohmylamb-1.0.1.dist-info/METADATA
ohmylamb-1.0.1.dist-info/WHEEL
ohmylamb-1.0.1.dist-info/top_level.txt
ohmylamb-1.0.1.dist-info/RECORD
