Metadata-Version: 2.1
Name: ohmylamb
Version: 1.0.1
Summary: A simple library to use AWS resources. And speedup development for lambda projects.
Home-page: https://gitlab.com/rewatiraman/ohmylamb/
Author: Rewati Raman
Author-email: rewati.raman@allergan.com
License: UNKNOWN
Platform: UNKNOWN
Classifier: Programming Language :: Python :: 3.7
Classifier: Operating System :: OS Independent
Requires-Dist: snowflake-connector-python
Requires-Dist: boto3
Requires-Dist: pandas
